qfinpy/__init__.py
qfinpy/core.py
qfinpy/tsa.py
qfinpy-0.0.2.dist-info/METADATA
qfinpy-0.0.2.dist-info/WHEEL
qfinpy-0.0.2.dist-info/licenses/LICENSE
qfinpy-0.0.2.dist-info/RECORD
