Metadata-Version: 2.3
Name: qfinpy
Version: 0.0.2
Summary: A powerful, easy-to-use library for Quantitative Finance
Project-URL: Homepage, https://github.com/bhawik-jani/qfinpy
Author-email: Bhawik Jani <bhawikjani1@gmail.com>
License: MIT License
License-File: LICENSE
Keywords: Algorithmic Trading,Finance,Option Pricing,Options Pricing,Portfolio Optimization,Quant,Quantitative Finance,Time Series Analysis
Classifier: License :: OSI Approved :: MIT License
Classifier: Operating System :: OS Independent
Classifier: Programming Language :: Python :: 3
Requires-Python: >=3.8
Requires-Dist: matplotlib
Requires-Dist: numba
Requires-Dist: numpy
Requires-Dist: scipy
